LICENSE
cei_crawler/__init__.py
cei_crawler/backend.py
cei_crawler/client.py
cei_crawler/constants.py
cei_crawler/crawlers.py
cei_crawler/exceptions.py
cei_crawler/models.py
cei_crawler/responses.py
cei_crawler/tests/__init__.py
cei_crawler/tests/test_constants.py
cei_crawler/tests/test_models.py
python_cei_crawler-0.1.2.dist-info/LICENSE
python_cei_crawler-0.1.2.dist-info/WHEEL
python_cei_crawler-0.1.2.dist-info/METADATA
python_cei_crawler-0.1.2.dist-info/RECORD
