Metadata-Version: 2.1
Name: python-cei-crawler
Version: 0.1.2
Summary: Biblioteca em python para obtenção de seus dados de investimentos na bolsa de valores (B3/CEI).
Home-page: https://github.com/MuriloScarpaSitonio/python-cei-crawler
License: MIT
Keywords: bolsa,cei,crawler,ações,dividendos
Author: MuriloScarpaSitonio
Author-email: muriloscarpa@gmail.com
Requires-Python: >=3.8,<4.0
Classifier: License :: OSI Approved :: MIT License
Classifier: Programming Language :: Python
Classifier: Programming Language :: Python :: 3
Classifier: Programming Language :: Python :: 3.8
Classifier: Programming Language :: Python :: 3.9
Requires-Dist: aiohttp (==3.7.4)
Requires-Dist: beautifulsoup4 (==4.10.0)
Project-URL: Repository, https://github.com/MuriloScarpaSitonio/python-cei-crawler
